retroquest/__init__.py
retroquest/__main__.py
retroquest/act1/Act1.py
retroquest/act1/Act1StoryFlags.py
retroquest/act1/__init__.py
retroquest/act1/characters/Blacksmith.py
retroquest/act1/characters/Deer.py
retroquest/act1/characters/Fisherman.py
retroquest/act1/characters/Grandmother.py
retroquest/act1/characters/Merchant.py
retroquest/act1/characters/Mira.py
retroquest/act1/characters/Priest.py
retroquest/act1/characters/Shopkeeper.py
retroquest/act1/characters/Villager.py
retroquest/act1/characters/__init__.py
retroquest/act1/items/AncientAmulet.py
retroquest/act1/items/Apple.py
retroquest/act1/items/Armor.py
retroquest/act1/items/Bread.py
retroquest/act1/items/BrokenShovel.py
retroquest/act1/items/Bucket.py
retroquest/act1/items/Bush.py
retroquest/act1/items/Candle.py
retroquest/act1/items/Chicken.py
retroquest/act1/items/Coin.py
retroquest/act1/items/DullKnife.py
retroquest/act1/items/Egg.py
retroquest/act1/items/EliorsJournal.py
retroquest/act1/items/ExtendedMagneticFishingRod.py
retroquest/act1/items/FadedPhotograph.py
retroquest/act1/items/Feather.py
retroquest/act1/items/Fish.py
retroquest/act1/items/FishingRod.py
retroquest/act1/items/HealingHerb.py
retroquest/act1/items/Horseshoe.py
retroquest/act1/items/Key.py
retroquest/act1/items/Lantern.py
retroquest/act1/items/Locket.py
retroquest/act1/items/Magnet.py
retroquest/act1/items/MagneticFishingRod.py
retroquest/act1/items/Map.py
retroquest/act1/items/Matches.py
retroquest/act1/items/Mechanism.py
retroquest/act1/items/MillstoneFragment.py
retroquest/act1/items/MysteriousBox.py
retroquest/act1/items/OldNotice.py
retroquest/act1/items/PrayerBook.py
retroquest/act1/items/RareFlower.py
retroquest/act1/items/River.py
retroquest/act1/items/Rope.py
retroquest/act1/items/RustyHoe.py
retroquest/act1/items/RustySaw.py
retroquest/act1/items/SackOfFlour.py
retroquest/act1/items/SharpKnife.py
retroquest/act1/items/ShedDoor.py
retroquest/act1/items/ShinyPebble.py
retroquest/act1/items/ShinyRing.py
retroquest-0.2.2.dist-info/METADATA
retroquest-0.2.2.dist-info/WHEEL
retroquest-0.2.2.dist-info/licenses/LICENSE
retroquest-0.2.2.dist-info/RECORD
