Metadata-Version: 2.4
Name: retroquest
Version: 0.2.2
Summary: A retro style text based adventure game.
Project-URL: bugs, https://github.com/rmstdope/retroquest/issues
Project-URL: homepage, https://github.com/rmstdope/retroquest
Author-email: Henrik Kurelid <henrik@kurelid.se>
Maintainer-email: Henrik Kurelid <henrik@kurelid.se>
License: MIT License
License-File: LICENSE
Keywords: adventure,game,interactive-fiction,retro,text-adventure
Classifier: Development Status :: 3 - Alpha
Classifier: Environment :: Console
Classifier: Intended Audience :: End Users/Desktop
Classifier: Programming Language :: Python :: 3
Requires-Dist: prompt-toolkit
Requires-Dist: pygame>=2.0.0
Requires-Dist: textual>=6.2.1
Provides-Extra: dev
Requires-Dist: pytest; extra == 'dev'
Requires-Dist: pytest-cov; extra == 'dev'
